{
    "photos": {
        "page": 1,
        "pages": 1,
        "perpage": 100,
        "total": 15,
        "photo": [
            {
                "id": "53083720052",
                "owner": "196568425@N05",
                "secret": "280372498e",
                "server": "65535",
                "farm": 66,
                "title": "16",
                "ispublic": 1,
                "isfriend": 0,
                "isfamily": 0
            },
            {
                "id": "53084284066",
                "owner": "196568425@N05",
                "secret": "afd3d3721b",
                "server": "65535",
                "farm": 66,
                "title": "15",
                "ispublic": 1,
                "isfriend": 0,
                "isfamily": 0
            },
            {
                "id": "53084284221",
                "owner": "196568425@N05",
                "secret": "55769cfdf5",
                "server": "65535",
                "farm": 66,
                "title": "14",
                "ispublic": 1,
                "isfriend": 0,
                "isfamily": 0
            },
            {
                "id": "53084779588",
                "owner": "196568425@N05",
                "secret": "26475fcc97",
                "server": "65535",
                "farm": 66,
                "title": "13",
                "ispublic": 1,
                "isfriend": 0,
                "isfamily": 0
            },
            {
                "id": "53084473809",
                "owner": "196568425@N05",
                "secret": "a9fd3b3c13",
                "server": "65535",
                "farm": 66,
                "title": "12",
                "ispublic": 1,
                "isfriend": 0,
                "isfamily": 0
            },
            {
                "id": "53084693640",
                "owner": "196568425@N05",
                "secret": "eda6ed091c",
                "server": "65535",
                "farm": 66,
                "title": "11",
                "ispublic": 1,
                "isfriend": 0,
                "isfamily": 0
            },
            {
                "id": "53084691035",
                "owner": "196568425@N05",
                "secret": "e868d60798",
                "server": "65535",
                "farm": 66,
                "title": "10",
                "ispublic": 1,
                "isfriend": 0,
                "isfamily": 0
            },
            {
                "id": "53084691040",
                "owner": "196568425@N05",
                "secret": "ef371103d0",
                "server": "65535",
                "farm": 66,
                "title": "9",
                "ispublic": 1,
                "isfriend": 0,
                "isfamily": 0
            },
            {
                "id": "53084779513",
                "owner": "196568425@N05",
                "secret": "c1f32e00fb",
                "server": "65535",
                "farm": 66,
                "title": "8",
                "ispublic": 1,
                "isfriend": 0,
                "isfamily": 0
            },
            {
                "id": "53084779533",
                "owner": "196568425@N05",
                "secret": "0e3a0da595",
                "server": "65535",
                "farm": 66,
                "title": "7",
                "ispublic": 1,
                "isfriend": 0,
                "isfamily": 0
            },
            {
                "id": "53083717002",
                "owner": "196568425@N05",
                "secret": "2381aeaa99",
                "server": "65535",
                "farm": 66,
                "title": "6",
                "ispublic": 1,
                "isfriend": 0,
                "isfamily": 0
            },
            {
                "id": "53084690195",
                "owner": "196568425@N05",
                "secret": "c7f3ab9171",
                "server": "65535",
                "farm": 66,
                "title": "5",
                "ispublic": 1,
                "isfriend": 0,
                "isfamily": 0
            },
            {
                "id": "53084472959",
                "owner": "196568425@N05",
                "secret": "7c5357f91c",
                "server": "65535",
                "farm": 66,
                "title": "4",
                "ispublic": 1,
                "isfriend": 0,
                "isfamily": 0
            },
            {
                "id": "53084778843",
                "owner": "196568425@N05",
                "secret": "367f6c98fb",
                "server": "65535",
                "farm": 66,
                "title": "3",
                "ispublic": 1,
                "isfriend": 0,
                "isfamily": 0
            },
            {
                "id": "53084472749",
                "owner": "196568425@N05",
                "secret": "50b1394f07",
                "server": "65535",
                "farm": 66,
                "title": "2",
                "ispublic": 1,
                "isfriend": 0,
                "isfamily": 0
            },
            {
                "id": "53084472694",
                "owner": "196568425@N05",
                "secret": "2e6608305c",
                "server": "65535",
                "farm": 66,
                "title": "1",
                "ispublic": 1,
                "isfriend": 0,
                "isfamily": 0
            }
        ]
    },
    "stat": "ok"
}